oganesson/VERSION
oganesson/__init__.py
oganesson/__main__.py
oganesson/cli.py
oganesson/ogai.py
oganesson/ogstructure.py
oganesson/version.py
oganesson/descriptors/__init__.py
oganesson/descriptors/bacd.py
oganesson/descriptors/descriptors.py
oganesson/descriptors/dscribe.py
oganesson/descriptors/rosa.py
oganesson/descriptors/symmetry_functions.py
oganesson/genetic_algorithms/__init__.py
oganesson/genetic_algorithms/particle_mutations.py
oganesson/io/__init__.py
oganesson/io/vasp.py
oganesson/pes_models/__init__.py
oganesson/pes_models/diep_pes/model.json
oganesson/pes_models/diep_pes/model.pt
oganesson/pes_models/diep_pes/state.pt
oganesson/utilities/__init__.py
oganesson/utilities/atomic_data.py
oganesson/utilities/bonds_dictionary.py
oganesson/utilities/constants.py
oganesson/utilities/graphs.py
oganesson-0.1.47.dist-info/licenses/LICENSE
oganesson-0.1.47.dist-info/METADATA
oganesson-0.1.47.dist-info/WHEEL
oganesson-0.1.47.dist-info/entry_points.txt
oganesson-0.1.47.dist-info/top_level.txt
oganesson-0.1.47.dist-info/RECORD
