Metadata-Version: 2.4
Name: oganesson
Version: 0.1.47
Summary: oganesson enables rapid AI workflows for material science and chemistry
Home-page: https://github.com/oganesson-ai/oganesson
Author: Sherif Abdulkader Tawfik Abbas
Author-email: sherif.tawfic@gmail.com
License: mit
Keywords: ai,machine learning,material science
License-File: LICENSE
Requires-Dist: ase
Requires-Dist: pandas
Requires-Dist: numpy
Requires-Dist: pymatgen
Requires-Dist: matgl
Requires-Dist: bsym
Requires-Dist: diffusivity
Dynamic: author
Dynamic: author-email
Dynamic: description
Dynamic: description-content-type
Dynamic: home-page
Dynamic: keywords
Dynamic: license
Dynamic: license-file
Dynamic: requires-dist
Dynamic: summary
